aioseinfeld/__init__.py
aioseinfeld/__version__.py
aioseinfeld/seinfeld.py
aioseinfeld/types.py
aioseinfeld/tests/__init__.py
aioseinfeld/tests/__main__.py
aioseinfeld/tests/smoke.py
aioseinfeld-0.2.0.dist-info/LICENSE
aioseinfeld-0.2.0.dist-info/WHEEL
aioseinfeld-0.2.0.dist-info/METADATA
aioseinfeld-0.2.0.dist-info/RECORD
