Metadata-Version: 2.1
Name: aioseinfeld
Version: 0.2.0
Summary: What's the deal with asyncio?
Home-page: https://github.com/jreese/aioseinfeld
License: UNKNOWN
Author: John Reese
Author-email: john@noswap.com
Requires-Python: >=3.7
Classifier: Framework :: AsyncIO
Classifier: Intended Audience :: Developers
Classifier: License :: OSI Approved :: MIT License
Classifier: Topic :: Software Development :: Libraries
Requires-Dist: aiosqlite
